{
	"id": "UserRoleMenuGroup",
	"order": 3,
	"objects": [
		{
			"id": "UserRoleMenuGroup_OWNER_Dashboard",
			"type": "com.brijframwork.authorization.model.EOUserRoleMenuGroup",
			"name": "UserRoleMenuGroup",
			"properties": {
				"userRole": "LK@UserRole_OWNER",
				"menuGroup": "LK@GlobalMenuGroup_Dashboard"
			}
		},
		{
			"id": "UserRoleMenuGroup_OWNER_Orders",
			"type": "com.brijframwork.authorization.model.EOUserRoleMenuGroup",
			"name": "UserRoleMenuGroup",
			"properties": {
				"userRole": "LK@UserRole_OWNER",
				"menuGroup": "LK@GlobalMenuGroup_Orders"
			}
		},
		{
			"id": "UserRoleMenuGroup_OWNER_Products",
			"type": "com.brijframwork.authorization.model.EOUserRoleMenuGroup",
			"name": "UserRoleMenuGroup",
			"properties": {
				"userRole": "LK@UserRole_OWNER",
				"menuGroup": "LK@GlobalMenuGroup_Products"
			}
		},
		{
			"id": "UserRoleMenuGroup_OWNER_Vendor",
			"type": "com.brijframwork.authorization.model.EOUserRoleMenuGroup",
			"name": "UserRoleMenuGroup",
			"properties": {
				"userRole": "LK@UserRole_OWNER",
				"menuGroup": "LK@GlobalMenuGroup_Vendor"
			}
		},
		{
			"id": "UserRoleMenuGroup_OWNER_Setups",
			"type": "com.brijframwork.authorization.model.EOUserRoleMenuGroup",
			"name": "UserRoleMenuGroup",
			"properties": {
				"userRole": "LK@UserRole_OWNER",
				"menuGroup": "LK@GlobalMenuGroup_Setups"
			}
		},
		{
			"id": "UserRoleMenuGroup_OWNER_Userprofile",
			"type": "com.brijframwork.authorization.model.EOUserRoleMenuGroup",
			"name": "UserRoleMenuGroup",
			"properties": {
				"userRole": "LK@UserRole_OWNER",
				"menuGroup": "LK@GlobalMenuGroup_Userprofile"
			}
		},
		{
			"id": "UserRoleMenuGroup_MANAGER_Dashboard",
			"type": "com.brijframwork.authorization.model.EOUserRoleMenuGroup",
			"name": "UserRoleMenuGroup",
			"properties": {
				"userRole": "LK@UserRole_MANAGER",
				"menuGroup": "LK@GlobalMenuGroup_Dashboard"
			}
		},
		{
			"id": "UserRoleMenuGroup_MANAGER_Orders",
			"type": "com.brijframwork.authorization.model.EOUserRoleMenuGroup",
			"name": "UserRoleMenuGroup",
			"properties": {
				"userRole": "LK@UserRole_MANAGER",
				"menuGroup": "LK@GlobalMenuGroup_Orders"
			}
		},
		{
			"id": "UserRoleMenuGroup_MANAGER_Products",
			"type": "com.brijframwork.authorization.model.EOUserRoleMenuGroup",
			"name": "UserRoleMenuGroup",
			"properties": {
				"userRole": "LK@UserRole_MANAGER",
				"menuGroup": "LK@GlobalMenuGroup_Products"
			}
		},
		{
			"id": "UserRoleMenuGroup_MANAGER_Vendor",
			"type": "com.brijframwork.authorization.model.EOUserRoleMenuGroup",
			"name": "UserRoleMenuGroup",
			"properties": {
				"userRole": "LK@UserRole_MANAGER",
				"menuGroup": "LK@GlobalMenuGroup_Vendor"
			}
		},
		{
			"id": "UserRoleMenuGroup_MANAGER_Setups",
			"type": "com.brijframwork.authorization.model.EOUserRoleMenuGroup",
			"name": "UserRoleMenuGroup",
			"properties": {
				"userRole": "LK@UserRole_MANAGER",
				"menuGroup": "LK@GlobalMenuGroup_Setups"
			}
		},
		{
			"id": "UserRoleMenuGroup_MANAGER_Userprofile",
			"type": "com.brijframwork.authorization.model.EOUserRoleMenuGroup",
			"name": "UserRoleMenuGroup",
			"properties": {
				"userRole": "LK@UserRole_MANAGER",
				"menuGroup": "LK@GlobalMenuGroup_Userprofile"
			}
		},
		{
			"id": "UserRoleMenuGroup_SUPERVISOR_Dashboard",
			"type": "com.brijframwork.authorization.model.EOUserRoleMenuGroup",
			"name": "UserRoleMenuGroup",
			"properties": {
				"userRole": "LK@UserRole_SUPERVISOR",
				"menuGroup": "LK@GlobalMenuGroup_Dashboard"
			}
		},
		{
			"id": "UserRoleMenuGroup_SUPERVISOR_Orders",
			"type": "com.brijframwork.authorization.model.EOUserRoleMenuGroup",
			"name": "UserRoleMenuGroup",
			"properties": {
				"userRole": "LK@UserRole_SUPERVISOR",
				"menuGroup": "LK@GlobalMenuGroup_Orders"
			}
		},
		{
			"id": "UserRoleMenuGroup_SUPERVISOR_Products",
			"type": "com.brijframwork.authorization.model.EOUserRoleMenuGroup",
			"name": "UserRoleMenuGroup",
			"properties": {
				"userRole": "LK@UserRole_SUPERVISOR",
				"menuGroup": "LK@GlobalMenuGroup_Products"
			}
		},
		{
			"id": "UserRoleMenuGroup_SUPERVISOR_Vendor",
			"type": "com.brijframwork.authorization.model.EOUserRoleMenuGroup",
			"name": "UserRoleMenuGroup",
			"properties": {
				"userRole": "LK@UserRole_SUPERVISOR",
				"menuGroup": "LK@GlobalMenuGroup_Vendor"
			}
		},
		{
			"id": "UserRoleMenuGroup_SUPERVISOR_Userprofile",
			"type": "com.brijframwork.authorization.model.EOUserRoleMenuGroup",
			"name": "UserRoleMenuGroup",
			"properties": {
				"userRole": "LK@UserRole_SUPERVISOR",
				"menuGroup": "LK@GlobalMenuGroup_Userprofile"
			}
		},
		{
			"id": "UserRoleMenuGroup_CREW_Dashboard",
			"type": "com.brijframwork.authorization.model.EOUserRoleMenuGroup",
			"name": "UserRoleMenuGroup",
			"properties": {
				"userRole": "LK@UserRole_CREW",
				"menuGroup": "LK@GlobalMenuGroup_Dashboard"
			}
		},
		{
			"id": "UserRoleMenuGroup_CREW_Orders",
			"type": "com.brijframwork.authorization.model.EOUserRoleMenuGroup",
			"name": "UserRoleMenuGroup",
			"properties": {
				"userRole": "LK@UserRole_CREW",
				"menuGroup": "LK@GlobalMenuGroup_Orders"
			}
		},
		{
			"id": "UserRoleMenuGroup_CREW_Vendor",
			"type": "com.brijframwork.authorization.model.EOUserRoleMenuGroup",
			"name": "UserRoleMenuGroup",
			"properties": {
				"userRole": "LK@UserRole_CREW",
				"menuGroup": "LK@GlobalMenuGroup_Vendor"
			}
		},
		{
			"id": "UserRoleMenuGroup_CREW_Products",
			"type": "com.brijframwork.authorization.model.EOUserRoleMenuGroup",
			"name": "UserRoleMenuGroup",
			"properties": {
				"userRole": "LK@UserRole_CREW",
				"menuGroup": "LK@GlobalMenuGroup_Products"
			}
		},
		{
			"id": "UserRoleMenuGroup_CREW_Userprofile",
			"type": "com.brijframwork.authorization.model.EOUserRoleMenuGroup",
			"name": "UserRoleMenuGroup",
			"properties": {
				"userRole": "LK@UserRole_CREW",
				"menuGroup": "LK@GlobalMenuGroup_Userprofile"
			}
		}
	]
}